{"v":"5.10.0","fr":30,"ip":0,"op":91,"w":1000,"h":1500,"nm":"5","ddd":0,"assets":[{"id":"comp_0","nm":"pre-01","fr":30,"layers":[{"ddd":0,"ind":1,"ty":4,"nm":"like 3","sr":1,"ks":{"o":{"a":0,"k":100,"ix":11},"r":{"a":0,"k":0,"ix":10},"p":{"s":true,"x":{"a":0,"k":50,"ix":3},"y":{"a":0,"k":50,"ix":4}},"a":{"a":0,"k":[-354.42,-107.858,0],"ix":1,"l":2},"s":{"a":0,"k":[550,550,100],"ix":6,"l":2}},"ao":0,"shapes":[{"ty":"gr","it":[{"ind":0,"ty":"sh","ix":1,"ks":{"a":0,"k":{"i":[[0,0],[-0.151,0.097],[-0.01,2.156],[1.607,0.008],[0.457,-0.829],[1.003,0.004],[0.008,-1.848],[-2.808,-1.826],[-0.126,0]],"o":[[0.131,0.001],[2.823,-1.802],[0.009,-1.849],[-1.003,-0.005],[-0.44,-0.828],[-1.607,-0.007],[-0.009,2.156],[0.155,0.096],[0,0]],"v":[[-354.447,-103.141],[-353.977,-103.33],[-349.333,-109.405],[-352.199,-112.555],[-354.412,-111.179],[-356.607,-112.575],[-359.507,-109.45],[-354.914,-103.335],[-354.447,-103.141]],"c":false},"ix":2},"nm":"Path 1","mn":"ADBE Vector Shape - Group","hd":false},{"ty":"fl","c":{"a":0,"k":[0.427450980392,0.360784313725,0.898039215686,1],"ix":4},"o":{"a":0,"k":100,"ix":5},"r":1,"bm":0,"nm":"Fill 1","mn":"ADBE Vector Graphic - Fill","hd":false},{"ty":"tr","p":{"a":0,"k":[0,0],"ix":2},"a":{"a":0,"k":[0,0],"ix":1},"s":{"a":0,"k":[100,100],"ix":3},"r":{"a":0,"k":0,"ix":6},"o":{"a":0,"k":100,"ix":7},"sk":{"a":0,"k":0,"ix":4},"sa":{"a":0,"k":0,"ix":5},"nm":"Transform"}],"nm":"Group 2","np":2,"cix":2,"bm":0,"ix":1,"mn":"ADBE Vector Group","hd":false}],"ip":0,"op":31,"st":0,"ct":1,"bm":0}]}],"layers":[{"ddd":0,"ind":1,"ty":0,"nm":"pre-01","refId":"comp_0","sr":1,"ks":{"o":{"a":1,"k":[{"i":{"x":[0.25],"y":[1]},"o":{"x":[0.75],"y":[0]},"t":54,"s":[100]},{"t":84,"s":[0]}],"ix":11},"r":{"a":1,"k":[{"i":{"x":[0.667],"y":[1]},"o":{"x":[0.75],"y":[0]},"t":54,"s":[0]},{"t":84,"s":[190]}],"ix":10},"p":{"a":1,"k":[{"i":{"x":0.25,"y":1},"o":{"x":0.333,"y":0},"t":54,"s":[500,51,0],"to":[-580,405,0],"ti":[-376.899,-485.396,0]},{"t":84,"s":[630.899,957.396,0]}],"ix":2,"l":2},"a":{"a":0,"k":[50,50,0],"ix":1,"l":2},"s":{"a":1,"k":[{"i":{"x":[0.25,0.25,0.25],"y":[1,1,1]},"o":{"x":[0.333,0.333,0.333],"y":[0,0,0]},"t":54,"s":[0,0,100]},{"t":84,"s":[150,150,100]}],"ix":6,"l":2}},"ao":0,"w":100,"h":100,"ip":54,"op":85,"st":54,"ct":1,"bm":0},{"ddd":0,"ind":2,"ty":0,"nm":"pre-01","refId":"comp_0","sr":1,"ks":{"o":{"a":1,"k":[{"i":{"x":[0.25],"y":[1]},"o":{"x":[0.75],"y":[0]},"t":53,"s":[100]},{"t":83,"s":[0]}],"ix":11},"r":{"a":1,"k":[{"i":{"x":[0.667],"y":[1]},"o":{"x":[0.75],"y":[0]},"t":53,"s":[0]},{"t":83,"s":[190]}],"ix":10},"p":{"a":1,"k":[{"i":{"x":0.25,"y":1},"o":{"x":0.333,"y":0},"t":53,"s":[500,51,0],"to":[484,193,0],"ti":[-292.899,-373.396,0]},{"t":83,"s":[918.899,957.396,0]}],"ix":2,"l":2},"a":{"a":0,"k":[50,50,0],"ix":1,"l":2},"s":{"a":1,"k":[{"i":{"x":[0.25,0.25,0.25],"y":[1,1,1]},"o":{"x":[0.333,0.333,0.333],"y":[0,0,0]},"t":53,"s":[0,0,100]},{"t":83,"s":[150,150,100]}],"ix":6,"l":2}},"ao":0,"w":100,"h":100,"ip":53,"op":84,"st":53,"ct":1,"bm":0},{"ddd":0,"ind":3,"ty":0,"nm":"pre-01","refId":"comp_0","sr":1,"ks":{"o":{"a":1,"k":[{"i":{"x":[0.25],"y":[1]},"o":{"x":[0.75],"y":[0]},"t":52,"s":[100]},{"t":82,"s":[0]}],"ix":11},"r":{"a":1,"k":[{"i":{"x":[0.25],"y":[1]},"o":{"x":[0.333],"y":[0]},"t":52,"s":[0]},{"t":82,"s":[360]}],"ix":10},"p":{"a":1,"k":[{"i":{"x":0.25,"y":1},"o":{"x":0.333,"y":0},"t":52,"s":[500,51,0],"to":[0,0,0],"ti":[673.101,-839.396,0]},{"t":82,"s":[150.899,957.396,0]}],"ix":2,"l":2},"a":{"a":0,"k":[50,50,0],"ix":1,"l":2},"s":{"a":1,"k":[{"i":{"x":[0.25,0.25,0.25],"y":[1,1,1]},"o":{"x":[0.333,0.333,0.333],"y":[0,0,0]},"t":52,"s":[0,0,100]},{"t":82,"s":[150,150,100]}],"ix":6,"l":2}},"ao":0,"w":100,"h":100,"ip":52,"op":83,"st":52,"ct":1,"bm":0},{"ddd":0,"ind":4,"ty":0,"nm":"pre-01","refId":"comp_0","sr":1,"ks":{"o":{"a":1,"k":[{"i":{"x":[0.25],"y":[1]},"o":{"x":[0.75],"y":[0]},"t":51,"s":[100]},{"t":81,"s":[0]}],"ix":11},"r":{"a":1,"k":[{"i":{"x":[0.667],"y":[1]},"o":{"x":[0.75],"y":[0]},"t":51,"s":[0]},{"t":81,"s":[190]}],"ix":10},"p":{"a":1,"k":[{"i":{"x":0.25,"y":1},"o":{"x":0.333,"y":0},"t":51,"s":[500,51,0],"to":[0,0,0],"ti":[-718.899,-656.396,0]},{"t":81,"s":[801.899,957.396,0]}],"ix":2,"l":2},"a":{"a":0,"k":[50,50,0],"ix":1,"l":2},"s":{"a":1,"k":[{"i":{"x":[0.25,0.25,0.25],"y":[1,1,1]},"o":{"x":[0.333,0.333,0.333],"y":[0,0,0]},"t":51,"s":[0,0,100]},{"t":81,"s":[150,150,100]}],"ix":6,"l":2}},"ao":0,"w":100,"h":100,"ip":51,"op":82,"st":51,"ct":1,"bm":0},{"ddd":0,"ind":5,"ty":0,"nm":"pre-01","refId":"comp_0","sr":1,"ks":{"o":{"a":1,"k":[{"i":{"x":[0.25],"y":[1]},"o":{"x":[0.75],"y":[0]},"t":50,"s":[100]},{"t":80,"s":[0]}],"ix":11},"r":{"a":1,"k":[{"i":{"x":[0.667],"y":[1]},"o":{"x":[0.75],"y":[0]},"t":50,"s":[0]},{"t":80,"s":[190]}],"ix":10},"p":{"a":1,"k":[{"i":{"x":0.25,"y":1},"o":{"x":0.333,"y":0},"t":50,"s":[500,51,0],"to":[193,360,0],"ti":[6.101,-765.396,0]},{"t":80,"s":[218.899,957.396,0]}],"ix":2,"l":2},"a":{"a":0,"k":[50,50,0],"ix":1,"l":2},"s":{"a":1,"k":[{"i":{"x":[0.25,0.25,0.25],"y":[1,1,1]},"o":{"x":[0.333,0.333,0.333],"y":[0,0,0]},"t":50,"s":[0,0,100]},{"t":80,"s":[150,150,100]}],"ix":6,"l":2}},"ao":0,"w":100,"h":100,"ip":50,"op":81,"st":50,"ct":1,"bm":0},{"ddd":0,"ind":6,"ty":0,"nm":"pre-01","refId":"comp_0","sr":1,"ks":{"o":{"a":1,"k":[{"i":{"x":[0.25],"y":[1]},"o":{"x":[0.75],"y":[0]},"t":49,"s":[100]},{"t":79,"s":[0]}],"ix":11},"r":{"a":1,"k":[{"i":{"x":[0.667],"y":[1]},"o":{"x":[0.75],"y":[0]},"t":49,"s":[0]},{"t":79,"s":[-149]}],"ix":10},"p":{"a":1,"k":[{"i":{"x":0.25,"y":1},"o":{"x":0.333,"y":0},"t":49,"s":[500,51,0],"to":[349,252,0],"ti":[-218.899,-435.396,0]},{"t":79,"s":[717.899,957.396,0]}],"ix":2,"l":2},"a":{"a":0,"k":[50,50,0],"ix":1,"l":2},"s":{"a":1,"k":[{"i":{"x":[0.25,0.25,0.25],"y":[1,1,1]},"o":{"x":[0.333,0.333,0.333],"y":[0,0,0]},"t":49,"s":[0,0,100]},{"t":79,"s":[150,150,100]}],"ix":6,"l":2}},"ao":0,"w":100,"h":100,"ip":49,"op":80,"st":49,"ct":1,"bm":0},{"ddd":0,"ind":7,"ty":0,"nm":"pre-01","refId":"comp_0","sr":1,"ks":{"o":{"a":1,"k":[{"i":{"x":[0.25],"y":[1]},"o":{"x":[0.75],"y":[0]},"t":48,"s":[100]},{"t":78,"s":[0]}],"ix":11},"r":{"a":1,"k":[{"i":{"x":[0.667],"y":[1]},"o":{"x":[0.75],"y":[0]},"t":48,"s":[0]},{"t":78,"s":[190]}],"ix":10},"p":{"a":1,"k":[{"i":{"x":0.25,"y":1},"o":{"x":0.333,"y":0},"t":48,"s":[500,51,0],"to":[0,0,0],"ti":[63.101,-597.396,0]},{"t":78,"s":[866.899,957.396,0]}],"ix":2,"l":2},"a":{"a":0,"k":[50,50,0],"ix":1,"l":2},"s":{"a":1,"k":[{"i":{"x":[0.25,0.25,0.25],"y":[1,1,1]},"o":{"x":[0.333,0.333,0.333],"y":[0,0,0]},"t":48,"s":[0,0,100]},{"t":78,"s":[150,150,100]}],"ix":6,"l":2}},"ao":0,"w":100,"h":100,"ip":48,"op":79,"st":48,"ct":1,"bm":0},{"ddd":0,"ind":8,"ty":0,"nm":"pre-01","refId":"comp_0","sr":1,"ks":{"o":{"a":1,"k":[{"i":{"x":[0.25],"y":[1]},"o":{"x":[0.75],"y":[0]},"t":47,"s":[100]},{"t":77,"s":[0]}],"ix":11},"r":{"a":1,"k":[{"i":{"x":[0.25],"y":[1]},"o":{"x":[0.333],"y":[0]},"t":47,"s":[0]},{"t":77,"s":[360]}],"ix":10},"p":{"a":1,"k":[{"i":{"x":0.25,"y":1},"o":{"x":0.333,"y":0},"t":47,"s":[500,51,0],"to":[0,0,0],"ti":[-50.899,-813.396,0]},{"t":77,"s":[113.899,957.396,0]}],"ix":2,"l":2},"a":{"a":0,"k":[50,50,0],"ix":1,"l":2},"s":{"a":1,"k":[{"i":{"x":[0.25,0.25,0.25],"y":[1,1,1]},"o":{"x":[0.333,0.333,0.333],"y":[0,0,0]},"t":47,"s":[0,0,100]},{"t":77,"s":[150,150,100]}],"ix":6,"l":2}},"ao":0,"w":100,"h":100,"ip":47,"op":78,"st":47,"ct":1,"bm":0},{"ddd":0,"ind":9,"ty":0,"nm":"pre-01","refId":"comp_0","sr":1,"ks":{"o":{"a":1,"k":[{"i":{"x":[0.25],"y":[1]},"o":{"x":[0.75],"y":[0]},"t":46,"s":[100]},{"t":76,"s":[0]}],"ix":11},"r":{"a":1,"k":[{"i":{"x":[0.667],"y":[1]},"o":{"x":[0.75],"y":[0]},"t":46,"s":[0]},{"t":76,"s":[-149]}],"ix":10},"p":{"a":1,"k":[{"i":{"x":0.25,"y":1},"o":{"x":0.333,"y":0},"t":46,"s":[500,51,0],"to":[-236,327,0],"ti":[252.101,-476.396,0]},{"t":76,"s":[413.899,957.396,0]}],"ix":2,"l":2},"a":{"a":0,"k":[50,50,0],"ix":1,"l":2},"s":{"a":1,"k":[{"i":{"x":[0.25,0.25,0.25],"y":[1,1,1]},"o":{"x":[0.333,0.333,0.333],"y":[0,0,0]},"t":46,"s":[0,0,100]},{"t":76,"s":[150,150,100]}],"ix":6,"l":2}},"ao":0,"w":100,"h":100,"ip":46,"op":77,"st":46,"ct":1,"bm":0},{"ddd":0,"ind":10,"ty":0,"nm":"pre-01","refId":"comp_0","sr":1,"ks":{"o":{"a":1,"k":[{"i":{"x":[0.25],"y":[1]},"o":{"x":[0.75],"y":[0]},"t":45,"s":[100]},{"t":75,"s":[0]}],"ix":11},"r":{"a":1,"k":[{"i":{"x":[0.667],"y":[1]},"o":{"x":[0.75],"y":[0]},"t":45,"s":[0]},{"t":75,"s":[190]}],"ix":10},"p":{"a":1,"k":[{"i":{"x":0.25,"y":1},"o":{"x":0.333,"y":0},"t":45,"s":[500,51,0],"to":[0,0,0],"ti":[-428.899,-618.396,0]},{"t":75,"s":[547.899,957.396,0]}],"ix":2,"l":2},"a":{"a":0,"k":[50,50,0],"ix":1,"l":2},"s":{"a":1,"k":[{"i":{"x":[0.25,0.25,0.25],"y":[1,1,1]},"o":{"x":[0.333,0.333,0.333],"y":[0,0,0]},"t":45,"s":[0,0,100]},{"t":75,"s":[150,150,100]}],"ix":6,"l":2}},"ao":0,"w":100,"h":100,"ip":45,"op":76,"st":45,"ct":1,"bm":0},{"ddd":0,"ind":11,"ty":0,"nm":"pre-01","refId":"comp_0","sr":1,"ks":{"o":{"a":1,"k":[{"i":{"x":[0.25],"y":[1]},"o":{"x":[0.75],"y":[0]},"t":44,"s":[100]},{"t":74,"s":[0]}],"ix":11},"r":{"a":1,"k":[{"i":{"x":[0.25],"y":[1]},"o":{"x":[0.333],"y":[0]},"t":44,"s":[0]},{"t":74,"s":[360]}],"ix":10},"p":{"a":1,"k":[{"i":{"x":0.25,"y":1},"o":{"x":0.333,"y":0},"t":44,"s":[500,51,0],"to":[0,0,0],"ti":[321.101,-729.396,0]},{"t":74,"s":[290.899,957.396,0]}],"ix":2,"l":2},"a":{"a":0,"k":[50,50,0],"ix":1,"l":2},"s":{"a":1,"k":[{"i":{"x":[0.25,0.25,0.25],"y":[1,1,1]},"o":{"x":[0.333,0.333,0.333],"y":[0,0,0]},"t":44,"s":[0,0,100]},{"t":74,"s":[150,150,100]}],"ix":6,"l":2}},"ao":0,"w":100,"h":100,"ip":44,"op":75,"st":44,"ct":1,"bm":0},{"ddd":0,"ind":12,"ty":0,"nm":"pre-01","refId":"comp_0","sr":1,"ks":{"o":{"a":1,"k":[{"i":{"x":[0.25],"y":[1]},"o":{"x":[0.75],"y":[0]},"t":43,"s":[100]},{"t":73,"s":[0]}],"ix":11},"r":{"a":1,"k":[{"i":{"x":[0.667],"y":[1]},"o":{"x":[0.75],"y":[0]},"t":43,"s":[0]},{"t":73,"s":[190]}],"ix":10},"p":{"a":1,"k":[{"i":{"x":0.25,"y":1},"o":{"x":0.333,"y":0},"t":43,"s":[500,51,0],"to":[-580,405,0],"ti":[-376.899,-485.396,0]},{"t":73,"s":[630.899,1059.396,0]}],"ix":2,"l":2},"a":{"a":0,"k":[50,50,0],"ix":1,"l":2},"s":{"a":1,"k":[{"i":{"x":[0.25,0.25,0.25],"y":[1,1,1]},"o":{"x":[0.333,0.333,0.333],"y":[0,0,0]},"t":43,"s":[0,0,100]},{"t":73,"s":[150,150,100]}],"ix":6,"l":2}},"ao":0,"w":100,"h":100,"ip":43,"op":74,"st":43,"ct":1,"bm":0},{"ddd":0,"ind":13,"ty":0,"nm":"pre-01","refId":"comp_0","sr":1,"ks":{"o":{"a":1,"k":[{"i":{"x":[0.25],"y":[1]},"o":{"x":[0.75],"y":[0]},"t":42,"s":[100]},{"t":72,"s":[0]}],"ix":11},"r":{"a":1,"k":[{"i":{"x":[0.667],"y":[1]},"o":{"x":[0.75],"y":[0]},"t":42,"s":[0]},{"t":72,"s":[190]}],"ix":10},"p":{"a":1,"k":[{"i":{"x":0.25,"y":1},"o":{"x":0.333,"y":0},"t":42,"s":[500,51,0],"to":[484,193,0],"ti":[-292.899,-373.396,0]},{"t":72,"s":[918.899,1059.396,0]}],"ix":2,"l":2},"a":{"a":0,"k":[50,50,0],"ix":1,"l":2},"s":{"a":1,"k":[{"i":{"x":[0.25,0.25,0.25],"y":[1,1,1]},"o":{"x":[0.333,0.333,0.333],"y":[0,0,0]},"t":42,"s":[0,0,100]},{"t":72,"s":[150,150,100]}],"ix":6,"l":2}},"ao":0,"w":100,"h":100,"ip":42,"op":73,"st":42,"ct":1,"bm":0},{"ddd":0,"ind":14,"ty":0,"nm":"pre-01","refId":"comp_0","sr":1,"ks":{"o":{"a":1,"k":[{"i":{"x":[0.25],"y":[1]},"o":{"x":[0.75],"y":[0]},"t":41,"s":[100]},{"t":71,"s":[0]}],"ix":11},"r":{"a":1,"k":[{"i":{"x":[0.25],"y":[1]},"o":{"x":[0.333],"y":[0]},"t":41,"s":[0]},{"t":71,"s":[360]}],"ix":10},"p":{"a":1,"k":[{"i":{"x":0.25,"y":1},"o":{"x":0.333,"y":0},"t":41,"s":[500,51,0],"to":[0,0,0],"ti":[673.101,-839.396,0]},{"t":71,"s":[150.899,1059.396,0]}],"ix":2,"l":2},"a":{"a":0,"k":[50,50,0],"ix":1,"l":2},"s":{"a":1,"k":[{"i":{"x":[0.25,0.25,0.25],"y":[1,1,1]},"o":{"x":[0.333,0.333,0.333],"y":[0,0,0]},"t":41,"s":[0,0,100]},{"t":71,"s":[150,150,100]}],"ix":6,"l":2}},"ao":0,"w":100,"h":100,"ip":41,"op":72,"st":41,"ct":1,"bm":0},{"ddd":0,"ind":15,"ty":0,"nm":"pre-01","refId":"comp_0","sr":1,"ks":{"o":{"a":1,"k":[{"i":{"x":[0.25],"y":[1]},"o":{"x":[0.75],"y":[0]},"t":40,"s":[100]},{"t":70,"s":[0]}],"ix":11},"r":{"a":1,"k":[{"i":{"x":[0.667],"y":[1]},"o":{"x":[0.75],"y":[0]},"t":40,"s":[0]},{"t":70,"s":[190]}],"ix":10},"p":{"a":1,"k":[{"i":{"x":0.25,"y":1},"o":{"x":0.333,"y":0},"t":40,"s":[500,51,0],"to":[0,0,0],"ti":[-718.899,-656.396,0]},{"t":70,"s":[801.899,1059.396,0]}],"ix":2,"l":2},"a":{"a":0,"k":[50,50,0],"ix":1,"l":2},"s":{"a":1,"k":[{"i":{"x":[0.25,0.25,0.25],"y":[1,1,1]},"o":{"x":[0.333,0.333,0.333],"y":[0,0,0]},"t":40,"s":[0,0,100]},{"t":70,"s":[150,150,100]}],"ix":6,"l":2}},"ao":0,"w":100,"h":100,"ip":40,"op":71,"st":40,"ct":1,"bm":0},{"ddd":0,"ind":16,"ty":0,"nm":"pre-01","refId":"comp_0","sr":1,"ks":{"o":{"a":1,"k":[{"i":{"x":[0.25],"y":[1]},"o":{"x":[0.75],"y":[0]},"t":39,"s":[100]},{"t":69,"s":[0]}],"ix":11},"r":{"a":1,"k":[{"i":{"x":[0.667],"y":[1]},"o":{"x":[0.75],"y":[0]},"t":39,"s":[0]},{"t":69,"s":[190]}],"ix":10},"p":{"a":1,"k":[{"i":{"x":0.25,"y":1},"o":{"x":0.333,"y":0},"t":39,"s":[500,51,0],"to":[193,360,0],"ti":[6.101,-765.396,0]},{"t":69,"s":[218.899,1059.396,0]}],"ix":2,"l":2},"a":{"a":0,"k":[50,50,0],"ix":1,"l":2},"s":{"a":1,"k":[{"i":{"x":[0.25,0.25,0.25],"y":[1,1,1]},"o":{"x":[0.333,0.333,0.333],"y":[0,0,0]},"t":39,"s":[0,0,100]},{"t":69,"s":[150,150,100]}],"ix":6,"l":2}},"ao":0,"w":100,"h":100,"ip":39,"op":70,"st":39,"ct":1,"bm":0},{"ddd":0,"ind":17,"ty":0,"nm":"pre-01","refId":"comp_0","sr":1,"ks":{"o":{"a":1,"k":[{"i":{"x":[0.25],"y":[1]},"o":{"x":[0.75],"y":[0]},"t":38,"s":[100]},{"t":68,"s":[0]}],"ix":11},"r":{"a":1,"k":[{"i":{"x":[0.667],"y":[1]},"o":{"x":[0.75],"y":[0]},"t":38,"s":[0]},{"t":68,"s":[-149]}],"ix":10},"p":{"a":1,"k":[{"i":{"x":0.25,"y":1},"o":{"x":0.333,"y":0},"t":38,"s":[500,51,0],"to":[349,252,0],"ti":[-218.899,-435.396,0]},{"t":68,"s":[717.899,1059.396,0]}],"ix":2,"l":2},"a":{"a":0,"k":[50,50,0],"ix":1,"l":2},"s":{"a":1,"k":[{"i":{"x":[0.25,0.25,0.25],"y":[1,1,1]},"o":{"x":[0.333,0.333,0.333],"y":[0,0,0]},"t":38,"s":[0,0,100]},{"t":68,"s":[150,150,100]}],"ix":6,"l":2}},"ao":0,"w":100,"h":100,"ip":38,"op":69,"st":38,"ct":1,"bm":0},{"ddd":0,"ind":18,"ty":0,"nm":"pre-01","refId":"comp_0","sr":1,"ks":{"o":{"a":1,"k":[{"i":{"x":[0.25],"y":[1]},"o":{"x":[0.75],"y":[0]},"t":37,"s":[100]},{"t":67,"s":[0]}],"ix":11},"r":{"a":1,"k":[{"i":{"x":[0.667],"y":[1]},"o":{"x":[0.75],"y":[0]},"t":37,"s":[0]},{"t":67,"s":[190]}],"ix":10},"p":{"a":1,"k":[{"i":{"x":0.25,"y":1},"o":{"x":0.333,"y":0},"t":37,"s":[500,51,0],"to":[0,0,0],"ti":[63.101,-597.396,0]},{"t":67,"s":[866.899,1059.396,0]}],"ix":2,"l":2},"a":{"a":0,"k":[50,50,0],"ix":1,"l":2},"s":{"a":1,"k":[{"i":{"x":[0.25,0.25,0.25],"y":[1,1,1]},"o":{"x":[0.333,0.333,0.333],"y":[0,0,0]},"t":37,"s":[0,0,100]},{"t":67,"s":[150,150,100]}],"ix":6,"l":2}},"ao":0,"w":100,"h":100,"ip":37,"op":68,"st":37,"ct":1,"bm":0},{"ddd":0,"ind":19,"ty":0,"nm":"pre-01","refId":"comp_0","sr":1,"ks":{"o":{"a":1,"k":[{"i":{"x":[0.25],"y":[1]},"o":{"x":[0.75],"y":[0]},"t":36,"s":[100]},{"t":66,"s":[0]}],"ix":11},"r":{"a":1,"k":[{"i":{"x":[0.25],"y":[1]},"o":{"x":[0.333],"y":[0]},"t":36,"s":[0]},{"t":66,"s":[360]}],"ix":10},"p":{"a":1,"k":[{"i":{"x":0.25,"y":1},"o":{"x":0.333,"y":0},"t":36,"s":[500,51,0],"to":[0,0,0],"ti":[-50.899,-813.396,0]},{"t":66,"s":[113.899,1059.396,0]}],"ix":2,"l":2},"a":{"a":0,"k":[50,50,0],"ix":1,"l":2},"s":{"a":1,"k":[{"i":{"x":[0.25,0.25,0.25],"y":[1,1,1]},"o":{"x":[0.333,0.333,0.333],"y":[0,0,0]},"t":36,"s":[0,0,100]},{"t":66,"s":[150,150,100]}],"ix":6,"l":2}},"ao":0,"w":100,"h":100,"ip":36,"op":67,"st":36,"ct":1,"bm":0},{"ddd":0,"ind":20,"ty":0,"nm":"pre-01","refId":"comp_0","sr":1,"ks":{"o":{"a":1,"k":[{"i":{"x":[0.25],"y":[1]},"o":{"x":[0.75],"y":[0]},"t":35,"s":[100]},{"t":65,"s":[0]}],"ix":11},"r":{"a":1,"k":[{"i":{"x":[0.667],"y":[1]},"o":{"x":[0.75],"y":[0]},"t":35,"s":[0]},{"t":65,"s":[-149]}],"ix":10},"p":{"a":1,"k":[{"i":{"x":0.25,"y":1},"o":{"x":0.333,"y":0},"t":35,"s":[500,51,0],"to":[-236,327,0],"ti":[252.101,-476.396,0]},{"t":65,"s":[413.899,1059.396,0]}],"ix":2,"l":2},"a":{"a":0,"k":[50,50,0],"ix":1,"l":2},"s":{"a":1,"k":[{"i":{"x":[0.25,0.25,0.25],"y":[1,1,1]},"o":{"x":[0.333,0.333,0.333],"y":[0,0,0]},"t":35,"s":[0,0,100]},{"t":65,"s":[150,150,100]}],"ix":6,"l":2}},"ao":0,"w":100,"h":100,"ip":35,"op":66,"st":35,"ct":1,"bm":0},{"ddd":0,"ind":21,"ty":0,"nm":"pre-01","refId":"comp_0","sr":1,"ks":{"o":{"a":1,"k":[{"i":{"x":[0.25],"y":[1]},"o":{"x":[0.75],"y":[0]},"t":34,"s":[100]},{"t":64,"s":[0]}],"ix":11},"r":{"a":1,"k":[{"i":{"x":[0.667],"y":[1]},"o":{"x":[0.75],"y":[0]},"t":34,"s":[0]},{"t":64,"s":[190]}],"ix":10},"p":{"a":1,"k":[{"i":{"x":0.25,"y":1},"o":{"x":0.333,"y":0},"t":34,"s":[500,51,0],"to":[0,0,0],"ti":[-428.899,-618.396,0]},{"t":64,"s":[547.899,1059.396,0]}],"ix":2,"l":2},"a":{"a":0,"k":[50,50,0],"ix":1,"l":2},"s":{"a":1,"k":[{"i":{"x":[0.25,0.25,0.25],"y":[1,1,1]},"o":{"x":[0.333,0.333,0.333],"y":[0,0,0]},"t":34,"s":[0,0,100]},{"t":64,"s":[150,150,100]}],"ix":6,"l":2}},"ao":0,"w":100,"h":100,"ip":34,"op":65,"st":34,"ct":1,"bm":0},{"ddd":0,"ind":22,"ty":0,"nm":"pre-01","refId":"comp_0","sr":1,"ks":{"o":{"a":1,"k":[{"i":{"x":[0.25],"y":[1]},"o":{"x":[0.75],"y":[0]},"t":33,"s":[100]},{"t":63,"s":[0]}],"ix":11},"r":{"a":1,"k":[{"i":{"x":[0.25],"y":[1]},"o":{"x":[0.333],"y":[0]},"t":33,"s":[0]},{"t":63,"s":[360]}],"ix":10},"p":{"a":1,"k":[{"i":{"x":0.25,"y":1},"o":{"x":0.333,"y":0},"t":33,"s":[500,51,0],"to":[0,0,0],"ti":[321.101,-729.396,0]},{"t":63,"s":[290.899,1059.396,0]}],"ix":2,"l":2},"a":{"a":0,"k":[50,50,0],"ix":1,"l":2},"s":{"a":1,"k":[{"i":{"x":[0.25,0.25,0.25],"y":[1,1,1]},"o":{"x":[0.333,0.333,0.333],"y":[0,0,0]},"t":33,"s":[0,0,100]},{"t":63,"s":[150,150,100]}],"ix":6,"l":2}},"ao":0,"w":100,"h":100,"ip":33,"op":64,"st":33,"ct":1,"bm":0},{"ddd":0,"ind":23,"ty":0,"nm":"pre-01","refId":"comp_0","sr":1,"ks":{"o":{"a":1,"k":[{"i":{"x":[0.25],"y":[1]},"o":{"x":[0.75],"y":[0]},"t":32,"s":[100]},{"t":62,"s":[0]}],"ix":11},"r":{"a":1,"k":[{"i":{"x":[0.667],"y":[1]},"o":{"x":[0.75],"y":[0]},"t":32,"s":[0]},{"t":62,"s":[190]}],"ix":10},"p":{"a":1,"k":[{"i":{"x":0.25,"y":1},"o":{"x":0.333,"y":0},"t":32,"s":[500,51,0],"to":[-580,405,0],"ti":[-376.899,-485.396,0]},{"t":62,"s":[630.899,1179.396,0]}],"ix":2,"l":2},"a":{"a":0,"k":[50,50,0],"ix":1,"l":2},"s":{"a":1,"k":[{"i":{"x":[0.25,0.25,0.25],"y":[1,1,1]},"o":{"x":[0.333,0.333,0.333],"y":[0,0,0]},"t":32,"s":[0,0,100]},{"t":62,"s":[150,150,100]}],"ix":6,"l":2}},"ao":0,"w":100,"h":100,"ip":32,"op":63,"st":32,"ct":1,"bm":0},{"ddd":0,"ind":24,"ty":0,"nm":"pre-01","refId":"comp_0","sr":1,"ks":{"o":{"a":1,"k":[{"i":{"x":[0.25],"y":[1]},"o":{"x":[0.75],"y":[0]},"t":31,"s":[100]},{"t":61,"s":[0]}],"ix":11},"r":{"a":1,"k":[{"i":{"x":[0.667],"y":[1]},"o":{"x":[0.75],"y":[0]},"t":31,"s":[0]},{"t":61,"s":[190]}],"ix":10},"p":{"a":1,"k":[{"i":{"x":0.25,"y":1},"o":{"x":0.333,"y":0},"t":31,"s":[500,51,0],"to":[484,193,0],"ti":[-292.899,-373.396,0]},{"t":61,"s":[918.899,1179.396,0]}],"ix":2,"l":2},"a":{"a":0,"k":[50,50,0],"ix":1,"l":2},"s":{"a":1,"k":[{"i":{"x":[0.25,0.25,0.25],"y":[1,1,1]},"o":{"x":[0.333,0.333,0.333],"y":[0,0,0]},"t":31,"s":[0,0,100]},{"t":61,"s":[150,150,100]}],"ix":6,"l":2}},"ao":0,"w":100,"h":100,"ip":31,"op":62,"st":31,"ct":1,"bm":0},{"ddd":0,"ind":25,"ty":0,"nm":"pre-01","refId":"comp_0","sr":1,"ks":{"o":{"a":1,"k":[{"i":{"x":[0.25],"y":[1]},"o":{"x":[0.75],"y":[0]},"t":30,"s":[100]},{"t":60,"s":[0]}],"ix":11},"r":{"a":1,"k":[{"i":{"x":[0.25],"y":[1]},"o":{"x":[0.333],"y":[0]},"t":30,"s":[0]},{"t":60,"s":[360]}],"ix":10},"p":{"a":1,"k":[{"i":{"x":0.25,"y":1},"o":{"x":0.333,"y":0},"t":30,"s":[500,51,0],"to":[0,0,0],"ti":[673.101,-839.396,0]},{"t":60,"s":[150.899,1179.396,0]}],"ix":2,"l":2},"a":{"a":0,"k":[50,50,0],"ix":1,"l":2},"s":{"a":1,"k":[{"i":{"x":[0.25,0.25,0.25],"y":[1,1,1]},"o":{"x":[0.333,0.333,0.333],"y":[0,0,0]},"t":30,"s":[0,0,100]},{"t":60,"s":[150,150,100]}],"ix":6,"l":2}},"ao":0,"w":100,"h":100,"ip":30,"op":61,"st":30,"ct":1,"bm":0},{"ddd":0,"ind":26,"ty":0,"nm":"pre-01","refId":"comp_0","sr":1,"ks":{"o":{"a":1,"k":[{"i":{"x":[0.25],"y":[1]},"o":{"x":[0.75],"y":[0]},"t":29,"s":[100]},{"t":59,"s":[0]}],"ix":11},"r":{"a":1,"k":[{"i":{"x":[0.667],"y":[1]},"o":{"x":[0.75],"y":[0]},"t":29,"s":[0]},{"t":59,"s":[190]}],"ix":10},"p":{"a":1,"k":[{"i":{"x":0.25,"y":1},"o":{"x":0.333,"y":0},"t":29,"s":[500,51,0],"to":[0,0,0],"ti":[-718.899,-656.396,0]},{"t":59,"s":[801.899,1179.396,0]}],"ix":2,"l":2},"a":{"a":0,"k":[50,50,0],"ix":1,"l":2},"s":{"a":1,"k":[{"i":{"x":[0.25,0.25,0.25],"y":[1,1,1]},"o":{"x":[0.333,0.333,0.333],"y":[0,0,0]},"t":29,"s":[0,0,100]},{"t":59,"s":[150,150,100]}],"ix":6,"l":2}},"ao":0,"w":100,"h":100,"ip":29,"op":60,"st":29,"ct":1,"bm":0},{"ddd":0,"ind":27,"ty":0,"nm":"pre-01","refId":"comp_0","sr":1,"ks":{"o":{"a":1,"k":[{"i":{"x":[0.25],"y":[1]},"o":{"x":[0.75],"y":[0]},"t":28,"s":[100]},{"t":58,"s":[0]}],"ix":11},"r":{"a":1,"k":[{"i":{"x":[0.667],"y":[1]},"o":{"x":[0.75],"y":[0]},"t":28,"s":[0]},{"t":58,"s":[190]}],"ix":10},"p":{"a":1,"k":[{"i":{"x":0.25,"y":1},"o":{"x":0.333,"y":0},"t":28,"s":[500,51,0],"to":[193,360,0],"ti":[6.101,-765.396,0]},{"t":58,"s":[218.899,1179.396,0]}],"ix":2,"l":2},"a":{"a":0,"k":[50,50,0],"ix":1,"l":2},"s":{"a":1,"k":[{"i":{"x":[0.25,0.25,0.25],"y":[1,1,1]},"o":{"x":[0.333,0.333,0.333],"y":[0,0,0]},"t":28,"s":[0,0,100]},{"t":58,"s":[150,150,100]}],"ix":6,"l":2}},"ao":0,"w":100,"h":100,"ip":28,"op":59,"st":28,"ct":1,"bm":0},{"ddd":0,"ind":28,"ty":0,"nm":"pre-01","refId":"comp_0","sr":1,"ks":{"o":{"a":1,"k":[{"i":{"x":[0.25],"y":[1]},"o":{"x":[0.75],"y":[0]},"t":27,"s":[100]},{"t":57,"s":[0]}],"ix":11},"r":{"a":1,"k":[{"i":{"x":[0.667],"y":[1]},"o":{"x":[0.75],"y":[0]},"t":27,"s":[0]},{"t":57,"s":[-149]}],"ix":10},"p":{"a":1,"k":[{"i":{"x":0.25,"y":1},"o":{"x":0.333,"y":0},"t":27,"s":[500,51,0],"to":[349,252,0],"ti":[-218.899,-435.396,0]},{"t":57,"s":[717.899,1179.396,0]}],"ix":2,"l":2},"a":{"a":0,"k":[50,50,0],"ix":1,"l":2},"s":{"a":1,"k":[{"i":{"x":[0.25,0.25,0.25],"y":[1,1,1]},"o":{"x":[0.333,0.333,0.333],"y":[0,0,0]},"t":27,"s":[0,0,100]},{"t":57,"s":[150,150,100]}],"ix":6,"l":2}},"ao":0,"w":100,"h":100,"ip":27,"op":58,"st":27,"ct":1,"bm":0},{"ddd":0,"ind":29,"ty":0,"nm":"pre-01","refId":"comp_0","sr":1,"ks":{"o":{"a":1,"k":[{"i":{"x":[0.25],"y":[1]},"o":{"x":[0.75],"y":[0]},"t":26,"s":[100]},{"t":56,"s":[0]}],"ix":11},"r":{"a":1,"k":[{"i":{"x":[0.667],"y":[1]},"o":{"x":[0.75],"y":[0]},"t":26,"s":[0]},{"t":56,"s":[190]}],"ix":10},"p":{"a":1,"k":[{"i":{"x":0.25,"y":1},"o":{"x":0.333,"y":0},"t":26,"s":[500,51,0],"to":[0,0,0],"ti":[63.101,-597.396,0]},{"t":56,"s":[866.899,1179.396,0]}],"ix":2,"l":2},"a":{"a":0,"k":[50,50,0],"ix":1,"l":2},"s":{"a":1,"k":[{"i":{"x":[0.25,0.25,0.25],"y":[1,1,1]},"o":{"x":[0.333,0.333,0.333],"y":[0,0,0]},"t":26,"s":[0,0,100]},{"t":56,"s":[150,150,100]}],"ix":6,"l":2}},"ao":0,"w":100,"h":100,"ip":26,"op":57,"st":26,"ct":1,"bm":0},{"ddd":0,"ind":30,"ty":0,"nm":"pre-01","refId":"comp_0","sr":1,"ks":{"o":{"a":1,"k":[{"i":{"x":[0.25],"y":[1]},"o":{"x":[0.75],"y":[0]},"t":25,"s":[100]},{"t":55,"s":[0]}],"ix":11},"r":{"a":1,"k":[{"i":{"x":[0.25],"y":[1]},"o":{"x":[0.333],"y":[0]},"t":25,"s":[0]},{"t":55,"s":[360]}],"ix":10},"p":{"a":1,"k":[{"i":{"x":0.25,"y":1},"o":{"x":0.333,"y":0},"t":25,"s":[500,51,0],"to":[0,0,0],"ti":[-50.899,-813.396,0]},{"t":55,"s":[113.899,1179.396,0]}],"ix":2,"l":2},"a":{"a":0,"k":[50,50,0],"ix":1,"l":2},"s":{"a":1,"k":[{"i":{"x":[0.25,0.25,0.25],"y":[1,1,1]},"o":{"x":[0.333,0.333,0.333],"y":[0,0,0]},"t":25,"s":[0,0,100]},{"t":55,"s":[150,150,100]}],"ix":6,"l":2}},"ao":0,"w":100,"h":100,"ip":25,"op":56,"st":25,"ct":1,"bm":0},{"ddd":0,"ind":31,"ty":0,"nm":"pre-01","refId":"comp_0","sr":1,"ks":{"o":{"a":1,"k":[{"i":{"x":[0.25],"y":[1]},"o":{"x":[0.75],"y":[0]},"t":24,"s":[100]},{"t":54,"s":[0]}],"ix":11},"r":{"a":1,"k":[{"i":{"x":[0.667],"y":[1]},"o":{"x":[0.75],"y":[0]},"t":24,"s":[0]},{"t":54,"s":[-149]}],"ix":10},"p":{"a":1,"k":[{"i":{"x":0.25,"y":1},"o":{"x":0.333,"y":0},"t":24,"s":[500,51,0],"to":[-236,327,0],"ti":[252.101,-476.396,0]},{"t":54,"s":[413.899,1179.396,0]}],"ix":2,"l":2},"a":{"a":0,"k":[50,50,0],"ix":1,"l":2},"s":{"a":1,"k":[{"i":{"x":[0.25,0.25,0.25],"y":[1,1,1]},"o":{"x":[0.333,0.333,0.333],"y":[0,0,0]},"t":24,"s":[0,0,100]},{"t":54,"s":[150,150,100]}],"ix":6,"l":2}},"ao":0,"w":100,"h":100,"ip":24,"op":55,"st":24,"ct":1,"bm":0},{"ddd":0,"ind":32,"ty":0,"nm":"pre-01","refId":"comp_0","sr":1,"ks":{"o":{"a":1,"k":[{"i":{"x":[0.25],"y":[1]},"o":{"x":[0.75],"y":[0]},"t":23,"s":[100]},{"t":53,"s":[0]}],"ix":11},"r":{"a":1,"k":[{"i":{"x":[0.667],"y":[1]},"o":{"x":[0.75],"y":[0]},"t":23,"s":[0]},{"t":53,"s":[190]}],"ix":10},"p":{"a":1,"k":[{"i":{"x":0.25,"y":1},"o":{"x":0.333,"y":0},"t":23,"s":[500,51,0],"to":[0,0,0],"ti":[-428.899,-618.396,0]},{"t":53,"s":[547.899,1179.396,0]}],"ix":2,"l":2},"a":{"a":0,"k":[50,50,0],"ix":1,"l":2},"s":{"a":1,"k":[{"i":{"x":[0.25,0.25,0.25],"y":[1,1,1]},"o":{"x":[0.333,0.333,0.333],"y":[0,0,0]},"t":23,"s":[0,0,100]},{"t":53,"s":[150,150,100]}],"ix":6,"l":2}},"ao":0,"w":100,"h":100,"ip":23,"op":54,"st":23,"ct":1,"bm":0},{"ddd":0,"ind":33,"ty":0,"nm":"pre-01","refId":"comp_0","sr":1,"ks":{"o":{"a":1,"k":[{"i":{"x":[0.25],"y":[1]},"o":{"x":[0.75],"y":[0]},"t":22,"s":[100]},{"t":52,"s":[0]}],"ix":11},"r":{"a":1,"k":[{"i":{"x":[0.25],"y":[1]},"o":{"x":[0.333],"y":[0]},"t":22,"s":[0]},{"t":52,"s":[360]}],"ix":10},"p":{"a":1,"k":[{"i":{"x":0.25,"y":1},"o":{"x":0.333,"y":0},"t":22,"s":[500,51,0],"to":[0,0,0],"ti":[321.101,-729.396,0]},{"t":52,"s":[290.899,1179.396,0]}],"ix":2,"l":2},"a":{"a":0,"k":[50,50,0],"ix":1,"l":2},"s":{"a":1,"k":[{"i":{"x":[0.25,0.25,0.25],"y":[1,1,1]},"o":{"x":[0.333,0.333,0.333],"y":[0,0,0]},"t":22,"s":[0,0,100]},{"t":52,"s":[150,150,100]}],"ix":6,"l":2}},"ao":0,"w":100,"h":100,"ip":22,"op":53,"st":22,"ct":1,"bm":0},{"ddd":0,"ind":34,"ty":0,"nm":"pre-01","refId":"comp_0","sr":1,"ks":{"o":{"a":1,"k":[{"i":{"x":[0.25],"y":[1]},"o":{"x":[0.75],"y":[0]},"t":21,"s":[100]},{"t":51,"s":[0]}],"ix":11},"r":{"a":1,"k":[{"i":{"x":[0.667],"y":[1]},"o":{"x":[0.75],"y":[0]},"t":21,"s":[0]},{"t":51,"s":[190]}],"ix":10},"p":{"a":1,"k":[{"i":{"x":0.25,"y":1},"o":{"x":0.333,"y":0},"t":21,"s":[500,51,0],"to":[-580,405,0],"ti":[-376.899,-485.396,0]},{"t":51,"s":[630.899,1305.396,0]}],"ix":2,"l":2},"a":{"a":0,"k":[50,50,0],"ix":1,"l":2},"s":{"a":1,"k":[{"i":{"x":[0.25,0.25,0.25],"y":[1,1,1]},"o":{"x":[0.333,0.333,0.333],"y":[0,0,0]},"t":21,"s":[0,0,100]},{"t":51,"s":[150,150,100]}],"ix":6,"l":2}},"ao":0,"w":100,"h":100,"ip":21,"op":52,"st":21,"ct":1,"bm":0},{"ddd":0,"ind":35,"ty":0,"nm":"pre-01","refId":"comp_0","sr":1,"ks":{"o":{"a":1,"k":[{"i":{"x":[0.25],"y":[1]},"o":{"x":[0.75],"y":[0]},"t":20,"s":[100]},{"t":50,"s":[0]}],"ix":11},"r":{"a":1,"k":[{"i":{"x":[0.667],"y":[1]},"o":{"x":[0.75],"y":[0]},"t":20,"s":[0]},{"t":50,"s":[190]}],"ix":10},"p":{"a":1,"k":[{"i":{"x":0.25,"y":1},"o":{"x":0.333,"y":0},"t":20,"s":[500,51,0],"to":[484,193,0],"ti":[-292.899,-373.396,0]},{"t":50,"s":[918.899,1305.396,0]}],"ix":2,"l":2},"a":{"a":0,"k":[50,50,0],"ix":1,"l":2},"s":{"a":1,"k":[{"i":{"x":[0.25,0.25,0.25],"y":[1,1,1]},"o":{"x":[0.333,0.333,0.333],"y":[0,0,0]},"t":20,"s":[0,0,100]},{"t":50,"s":[150,150,100]}],"ix":6,"l":2}},"ao":0,"w":100,"h":100,"ip":20,"op":51,"st":20,"ct":1,"bm":0},{"ddd":0,"ind":36,"ty":0,"nm":"pre-01","refId":"comp_0","sr":1,"ks":{"o":{"a":1,"k":[{"i":{"x":[0.25],"y":[1]},"o":{"x":[0.75],"y":[0]},"t":19,"s":[100]},{"t":49,"s":[0]}],"ix":11},"r":{"a":1,"k":[{"i":{"x":[0.25],"y":[1]},"o":{"x":[0.333],"y":[0]},"t":19,"s":[0]},{"t":49,"s":[360]}],"ix":10},"p":{"a":1,"k":[{"i":{"x":0.25,"y":1},"o":{"x":0.333,"y":0},"t":19,"s":[500,51,0],"to":[0,0,0],"ti":[673.101,-839.396,0]},{"t":49,"s":[150.899,1305.396,0]}],"ix":2,"l":2},"a":{"a":0,"k":[50,50,0],"ix":1,"l":2},"s":{"a":1,"k":[{"i":{"x":[0.25,0.25,0.25],"y":[1,1,1]},"o":{"x":[0.333,0.333,0.333],"y":[0,0,0]},"t":19,"s":[0,0,100]},{"t":49,"s":[150,150,100]}],"ix":6,"l":2}},"ao":0,"w":100,"h":100,"ip":19,"op":50,"st":19,"ct":1,"bm":0},{"ddd":0,"ind":37,"ty":0,"nm":"pre-01","refId":"comp_0","sr":1,"ks":{"o":{"a":1,"k":[{"i":{"x":[0.25],"y":[1]},"o":{"x":[0.75],"y":[0]},"t":18,"s":[100]},{"t":48,"s":[0]}],"ix":11},"r":{"a":1,"k":[{"i":{"x":[0.667],"y":[1]},"o":{"x":[0.75],"y":[0]},"t":18,"s":[0]},{"t":48,"s":[190]}],"ix":10},"p":{"a":1,"k":[{"i":{"x":0.25,"y":1},"o":{"x":0.333,"y":0},"t":18,"s":[500,51,0],"to":[0,0,0],"ti":[-718.899,-656.396,0]},{"t":48,"s":[801.899,1305.396,0]}],"ix":2,"l":2},"a":{"a":0,"k":[50,50,0],"ix":1,"l":2},"s":{"a":1,"k":[{"i":{"x":[0.25,0.25,0.25],"y":[1,1,1]},"o":{"x":[0.333,0.333,0.333],"y":[0,0,0]},"t":18,"s":[0,0,100]},{"t":48,"s":[150,150,100]}],"ix":6,"l":2}},"ao":0,"w":100,"h":100,"ip":18,"op":49,"st":18,"ct":1,"bm":0},{"ddd":0,"ind":38,"ty":0,"nm":"pre-01","refId":"comp_0","sr":1,"ks":{"o":{"a":1,"k":[{"i":{"x":[0.25],"y":[1]},"o":{"x":[0.75],"y":[0]},"t":17,"s":[100]},{"t":47,"s":[0]}],"ix":11},"r":{"a":1,"k":[{"i":{"x":[0.667],"y":[1]},"o":{"x":[0.75],"y":[0]},"t":17,"s":[0]},{"t":47,"s":[190]}],"ix":10},"p":{"a":1,"k":[{"i":{"x":0.25,"y":1},"o":{"x":0.333,"y":0},"t":17,"s":[500,51,0],"to":[193,360,0],"ti":[6.101,-765.396,0]},{"t":47,"s":[218.899,1305.396,0]}],"ix":2,"l":2},"a":{"a":0,"k":[50,50,0],"ix":1,"l":2},"s":{"a":1,"k":[{"i":{"x":[0.25,0.25,0.25],"y":[1,1,1]},"o":{"x":[0.333,0.333,0.333],"y":[0,0,0]},"t":17,"s":[0,0,100]},{"t":47,"s":[150,150,100]}],"ix":6,"l":2}},"ao":0,"w":100,"h":100,"ip":17,"op":48,"st":17,"ct":1,"bm":0},{"ddd":0,"ind":39,"ty":0,"nm":"pre-01","refId":"comp_0","sr":1,"ks":{"o":{"a":1,"k":[{"i":{"x":[0.25],"y":[1]},"o":{"x":[0.75],"y":[0]},"t":16,"s":[100]},{"t":46,"s":[0]}],"ix":11},"r":{"a":1,"k":[{"i":{"x":[0.667],"y":[1]},"o":{"x":[0.75],"y":[0]},"t":16,"s":[0]},{"t":46,"s":[-149]}],"ix":10},"p":{"a":1,"k":[{"i":{"x":0.25,"y":1},"o":{"x":0.333,"y":0},"t":16,"s":[500,51,0],"to":[349,252,0],"ti":[-218.899,-435.396,0]},{"t":46,"s":[717.899,1305.396,0]}],"ix":2,"l":2},"a":{"a":0,"k":[50,50,0],"ix":1,"l":2},"s":{"a":1,"k":[{"i":{"x":[0.25,0.25,0.25],"y":[1,1,1]},"o":{"x":[0.333,0.333,0.333],"y":[0,0,0]},"t":16,"s":[0,0,100]},{"t":46,"s":[150,150,100]}],"ix":6,"l":2}},"ao":0,"w":100,"h":100,"ip":16,"op":47,"st":16,"ct":1,"bm":0},{"ddd":0,"ind":40,"ty":0,"nm":"pre-01","refId":"comp_0","sr":1,"ks":{"o":{"a":1,"k":[{"i":{"x":[0.25],"y":[1]},"o":{"x":[0.75],"y":[0]},"t":15,"s":[100]},{"t":45,"s":[0]}],"ix":11},"r":{"a":1,"k":[{"i":{"x":[0.667],"y":[1]},"o":{"x":[0.75],"y":[0]},"t":15,"s":[0]},{"t":45,"s":[190]}],"ix":10},"p":{"a":1,"k":[{"i":{"x":0.25,"y":1},"o":{"x":0.333,"y":0},"t":15,"s":[500,51,0],"to":[0,0,0],"ti":[63.101,-597.396,0]},{"t":45,"s":[866.899,1305.396,0]}],"ix":2,"l":2},"a":{"a":0,"k":[50,50,0],"ix":1,"l":2},"s":{"a":1,"k":[{"i":{"x":[0.25,0.25,0.25],"y":[1,1,1]},"o":{"x":[0.333,0.333,0.333],"y":[0,0,0]},"t":15,"s":[0,0,100]},{"t":45,"s":[150,150,100]}],"ix":6,"l":2}},"ao":0,"w":100,"h":100,"ip":15,"op":46,"st":15,"ct":1,"bm":0},{"ddd":0,"ind":41,"ty":0,"nm":"pre-01","refId":"comp_0","sr":1,"ks":{"o":{"a":1,"k":[{"i":{"x":[0.25],"y":[1]},"o":{"x":[0.75],"y":[0]},"t":14,"s":[100]},{"t":44,"s":[0]}],"ix":11},"r":{"a":1,"k":[{"i":{"x":[0.25],"y":[1]},"o":{"x":[0.333],"y":[0]},"t":14,"s":[0]},{"t":44,"s":[360]}],"ix":10},"p":{"a":1,"k":[{"i":{"x":0.25,"y":1},"o":{"x":0.333,"y":0},"t":14,"s":[500,51,0],"to":[0,0,0],"ti":[-50.899,-813.396,0]},{"t":44,"s":[113.899,1305.396,0]}],"ix":2,"l":2},"a":{"a":0,"k":[50,50,0],"ix":1,"l":2},"s":{"a":1,"k":[{"i":{"x":[0.25,0.25,0.25],"y":[1,1,1]},"o":{"x":[0.333,0.333,0.333],"y":[0,0,0]},"t":14,"s":[0,0,100]},{"t":44,"s":[150,150,100]}],"ix":6,"l":2}},"ao":0,"w":100,"h":100,"ip":14,"op":45,"st":14,"ct":1,"bm":0},{"ddd":0,"ind":42,"ty":0,"nm":"pre-01","refId":"comp_0","sr":1,"ks":{"o":{"a":1,"k":[{"i":{"x":[0.25],"y":[1]},"o":{"x":[0.75],"y":[0]},"t":13,"s":[100]},{"t":43,"s":[0]}],"ix":11},"r":{"a":1,"k":[{"i":{"x":[0.667],"y":[1]},"o":{"x":[0.75],"y":[0]},"t":13,"s":[0]},{"t":43,"s":[-149]}],"ix":10},"p":{"a":1,"k":[{"i":{"x":0.25,"y":1},"o":{"x":0.333,"y":0},"t":13,"s":[500,51,0],"to":[-236,327,0],"ti":[252.101,-476.396,0]},{"t":43,"s":[413.899,1305.396,0]}],"ix":2,"l":2},"a":{"a":0,"k":[50,50,0],"ix":1,"l":2},"s":{"a":1,"k":[{"i":{"x":[0.25,0.25,0.25],"y":[1,1,1]},"o":{"x":[0.333,0.333,0.333],"y":[0,0,0]},"t":13,"s":[0,0,100]},{"t":43,"s":[150,150,100]}],"ix":6,"l":2}},"ao":0,"w":100,"h":100,"ip":13,"op":44,"st":13,"ct":1,"bm":0},{"ddd":0,"ind":43,"ty":0,"nm":"pre-01","refId":"comp_0","sr":1,"ks":{"o":{"a":1,"k":[{"i":{"x":[0.25],"y":[1]},"o":{"x":[0.75],"y":[0]},"t":12,"s":[100]},{"t":42,"s":[0]}],"ix":11},"r":{"a":1,"k":[{"i":{"x":[0.667],"y":[1]},"o":{"x":[0.75],"y":[0]},"t":12,"s":[0]},{"t":42,"s":[190]}],"ix":10},"p":{"a":1,"k":[{"i":{"x":0.25,"y":1},"o":{"x":0.333,"y":0},"t":12,"s":[500,51,0],"to":[0,0,0],"ti":[-428.899,-618.396,0]},{"t":42,"s":[547.899,1305.396,0]}],"ix":2,"l":2},"a":{"a":0,"k":[50,50,0],"ix":1,"l":2},"s":{"a":1,"k":[{"i":{"x":[0.25,0.25,0.25],"y":[1,1,1]},"o":{"x":[0.333,0.333,0.333],"y":[0,0,0]},"t":12,"s":[0,0,100]},{"t":42,"s":[150,150,100]}],"ix":6,"l":2}},"ao":0,"w":100,"h":100,"ip":12,"op":43,"st":12,"ct":1,"bm":0},{"ddd":0,"ind":44,"ty":0,"nm":"pre-01","refId":"comp_0","sr":1,"ks":{"o":{"a":1,"k":[{"i":{"x":[0.25],"y":[1]},"o":{"x":[0.75],"y":[0]},"t":11,"s":[100]},{"t":41,"s":[0]}],"ix":11},"r":{"a":1,"k":[{"i":{"x":[0.25],"y":[1]},"o":{"x":[0.333],"y":[0]},"t":11,"s":[0]},{"t":41,"s":[360]}],"ix":10},"p":{"a":1,"k":[{"i":{"x":0.25,"y":1},"o":{"x":0.333,"y":0},"t":11,"s":[500,51,0],"to":[0,0,0],"ti":[321.101,-729.396,0]},{"t":41,"s":[290.899,1305.396,0]}],"ix":2,"l":2},"a":{"a":0,"k":[50,50,0],"ix":1,"l":2},"s":{"a":1,"k":[{"i":{"x":[0.25,0.25,0.25],"y":[1,1,1]},"o":{"x":[0.333,0.333,0.333],"y":[0,0,0]},"t":11,"s":[0,0,100]},{"t":41,"s":[150,150,100]}],"ix":6,"l":2}},"ao":0,"w":100,"h":100,"ip":11,"op":42,"st":11,"ct":1,"bm":0},{"ddd":0,"ind":45,"ty":0,"nm":"pre-01","refId":"comp_0","sr":1,"ks":{"o":{"a":1,"k":[{"i":{"x":[0.25],"y":[1]},"o":{"x":[0.75],"y":[0]},"t":10,"s":[100]},{"t":40,"s":[0]}],"ix":11},"r":{"a":1,"k":[{"i":{"x":[0.667],"y":[1]},"o":{"x":[0.75],"y":[0]},"t":10,"s":[0]},{"t":40,"s":[190]}],"ix":10},"p":{"a":1,"k":[{"i":{"x":0.25,"y":1},"o":{"x":0.333,"y":0},"t":10,"s":[500,51,0],"to":[-580,405,0],"ti":[-376.899,-485.396,0]},{"t":40,"s":[630.899,1416.396,0]}],"ix":2,"l":2},"a":{"a":0,"k":[50,50,0],"ix":1,"l":2},"s":{"a":1,"k":[{"i":{"x":[0.25,0.25,0.25],"y":[1,1,1]},"o":{"x":[0.333,0.333,0.333],"y":[0,0,0]},"t":10,"s":[0,0,100]},{"t":40,"s":[150,150,100]}],"ix":6,"l":2}},"ao":0,"w":100,"h":100,"ip":10,"op":41,"st":10,"ct":1,"bm":0},{"ddd":0,"ind":46,"ty":0,"nm":"pre-01","refId":"comp_0","sr":1,"ks":{"o":{"a":1,"k":[{"i":{"x":[0.25],"y":[1]},"o":{"x":[0.75],"y":[0]},"t":9,"s":[100]},{"t":39,"s":[0]}],"ix":11},"r":{"a":1,"k":[{"i":{"x":[0.667],"y":[1]},"o":{"x":[0.75],"y":[0]},"t":9,"s":[0]},{"t":39,"s":[190]}],"ix":10},"p":{"a":1,"k":[{"i":{"x":0.25,"y":1},"o":{"x":0.333,"y":0},"t":9,"s":[500,51,0],"to":[484,193,0],"ti":[-292.899,-373.396,0]},{"t":39,"s":[918.899,1416.396,0]}],"ix":2,"l":2},"a":{"a":0,"k":[50,50,0],"ix":1,"l":2},"s":{"a":1,"k":[{"i":{"x":[0.25,0.25,0.25],"y":[1,1,1]},"o":{"x":[0.333,0.333,0.333],"y":[0,0,0]},"t":9,"s":[0,0,100]},{"t":39,"s":[150,150,100]}],"ix":6,"l":2}},"ao":0,"w":100,"h":100,"ip":9,"op":40,"st":9,"ct":1,"bm":0},{"ddd":0,"ind":47,"ty":0,"nm":"pre-01","refId":"comp_0","sr":1,"ks":{"o":{"a":1,"k":[{"i":{"x":[0.25],"y":[1]},"o":{"x":[0.75],"y":[0]},"t":8,"s":[100]},{"t":38,"s":[0]}],"ix":11},"r":{"a":1,"k":[{"i":{"x":[0.25],"y":[1]},"o":{"x":[0.333],"y":[0]},"t":8,"s":[0]},{"t":38,"s":[360]}],"ix":10},"p":{"a":1,"k":[{"i":{"x":0.25,"y":1},"o":{"x":0.333,"y":0},"t":8,"s":[500,51,0],"to":[0,0,0],"ti":[673.101,-839.396,0]},{"t":38,"s":[150.899,1416.396,0]}],"ix":2,"l":2},"a":{"a":0,"k":[50,50,0],"ix":1,"l":2},"s":{"a":1,"k":[{"i":{"x":[0.25,0.25,0.25],"y":[1,1,1]},"o":{"x":[0.333,0.333,0.333],"y":[0,0,0]},"t":8,"s":[0,0,100]},{"t":38,"s":[150,150,100]}],"ix":6,"l":2}},"ao":0,"w":100,"h":100,"ip":8,"op":39,"st":8,"ct":1,"bm":0},{"ddd":0,"ind":48,"ty":0,"nm":"pre-01","refId":"comp_0","sr":1,"ks":{"o":{"a":1,"k":[{"i":{"x":[0.25],"y":[1]},"o":{"x":[0.75],"y":[0]},"t":7,"s":[100]},{"t":37,"s":[0]}],"ix":11},"r":{"a":1,"k":[{"i":{"x":[0.667],"y":[1]},"o":{"x":[0.75],"y":[0]},"t":7,"s":[0]},{"t":37,"s":[190]}],"ix":10},"p":{"a":1,"k":[{"i":{"x":0.25,"y":1},"o":{"x":0.333,"y":0},"t":7,"s":[500,51,0],"to":[0,0,0],"ti":[-718.899,-656.396,0]},{"t":37,"s":[801.899,1416.396,0]}],"ix":2,"l":2},"a":{"a":0,"k":[50,50,0],"ix":1,"l":2},"s":{"a":1,"k":[{"i":{"x":[0.25,0.25,0.25],"y":[1,1,1]},"o":{"x":[0.333,0.333,0.333],"y":[0,0,0]},"t":7,"s":[0,0,100]},{"t":37,"s":[150,150,100]}],"ix":6,"l":2}},"ao":0,"w":100,"h":100,"ip":7,"op":38,"st":7,"ct":1,"bm":0},{"ddd":0,"ind":49,"ty":0,"nm":"pre-01","refId":"comp_0","sr":1,"ks":{"o":{"a":1,"k":[{"i":{"x":[0.25],"y":[1]},"o":{"x":[0.75],"y":[0]},"t":6,"s":[100]},{"t":36,"s":[0]}],"ix":11},"r":{"a":1,"k":[{"i":{"x":[0.667],"y":[1]},"o":{"x":[0.75],"y":[0]},"t":6,"s":[0]},{"t":36,"s":[190]}],"ix":10},"p":{"a":1,"k":[{"i":{"x":0.25,"y":1},"o":{"x":0.333,"y":0},"t":6,"s":[500,51,0],"to":[193,360,0],"ti":[6.101,-765.396,0]},{"t":36,"s":[218.899,1416.396,0]}],"ix":2,"l":2},"a":{"a":0,"k":[50,50,0],"ix":1,"l":2},"s":{"a":1,"k":[{"i":{"x":[0.25,0.25,0.25],"y":[1,1,1]},"o":{"x":[0.333,0.333,0.333],"y":[0,0,0]},"t":6,"s":[0,0,100]},{"t":36,"s":[150,150,100]}],"ix":6,"l":2}},"ao":0,"w":100,"h":100,"ip":6,"op":37,"st":6,"ct":1,"bm":0},{"ddd":0,"ind":50,"ty":0,"nm":"pre-01","refId":"comp_0","sr":1,"ks":{"o":{"a":1,"k":[{"i":{"x":[0.25],"y":[1]},"o":{"x":[0.75],"y":[0]},"t":5,"s":[100]},{"t":35,"s":[0]}],"ix":11},"r":{"a":1,"k":[{"i":{"x":[0.667],"y":[1]},"o":{"x":[0.75],"y":[0]},"t":5,"s":[0]},{"t":35,"s":[-149]}],"ix":10},"p":{"a":1,"k":[{"i":{"x":0.25,"y":1},"o":{"x":0.333,"y":0},"t":5,"s":[500,51,0],"to":[349,252,0],"ti":[-218.899,-435.396,0]},{"t":35,"s":[717.899,1416.396,0]}],"ix":2,"l":2},"a":{"a":0,"k":[50,50,0],"ix":1,"l":2},"s":{"a":1,"k":[{"i":{"x":[0.25,0.25,0.25],"y":[1,1,1]},"o":{"x":[0.333,0.333,0.333],"y":[0,0,0]},"t":5,"s":[0,0,100]},{"t":35,"s":[150,150,100]}],"ix":6,"l":2}},"ao":0,"w":100,"h":100,"ip":5,"op":36,"st":5,"ct":1,"bm":0},{"ddd":0,"ind":51,"ty":0,"nm":"pre-01","refId":"comp_0","sr":1,"ks":{"o":{"a":1,"k":[{"i":{"x":[0.25],"y":[1]},"o":{"x":[0.75],"y":[0]},"t":4,"s":[100]},{"t":34,"s":[0]}],"ix":11},"r":{"a":1,"k":[{"i":{"x":[0.667],"y":[1]},"o":{"x":[0.75],"y":[0]},"t":4,"s":[0]},{"t":34,"s":[190]}],"ix":10},"p":{"a":1,"k":[{"i":{"x":0.25,"y":1},"o":{"x":0.333,"y":0},"t":4,"s":[500,51,0],"to":[0,0,0],"ti":[63.101,-597.396,0]},{"t":34,"s":[866.899,1416.396,0]}],"ix":2,"l":2},"a":{"a":0,"k":[50,50,0],"ix":1,"l":2},"s":{"a":1,"k":[{"i":{"x":[0.25,0.25,0.25],"y":[1,1,1]},"o":{"x":[0.333,0.333,0.333],"y":[0,0,0]},"t":4,"s":[0,0,100]},{"t":34,"s":[150,150,100]}],"ix":6,"l":2}},"ao":0,"w":100,"h":100,"ip":4,"op":35,"st":4,"ct":1,"bm":0},{"ddd":0,"ind":52,"ty":0,"nm":"pre-01","refId":"comp_0","sr":1,"ks":{"o":{"a":1,"k":[{"i":{"x":[0.25],"y":[1]},"o":{"x":[0.75],"y":[0]},"t":3,"s":[100]},{"t":33,"s":[0]}],"ix":11},"r":{"a":1,"k":[{"i":{"x":[0.25],"y":[1]},"o":{"x":[0.333],"y":[0]},"t":3,"s":[0]},{"t":33,"s":[360]}],"ix":10},"p":{"a":1,"k":[{"i":{"x":0.25,"y":1},"o":{"x":0.333,"y":0},"t":3,"s":[500,51,0],"to":[0,0,0],"ti":[-50.899,-813.396,0]},{"t":33,"s":[113.899,1416.396,0]}],"ix":2,"l":2},"a":{"a":0,"k":[50,50,0],"ix":1,"l":2},"s":{"a":1,"k":[{"i":{"x":[0.25,0.25,0.25],"y":[1,1,1]},"o":{"x":[0.333,0.333,0.333],"y":[0,0,0]},"t":3,"s":[0,0,100]},{"t":33,"s":[150,150,100]}],"ix":6,"l":2}},"ao":0,"w":100,"h":100,"ip":3,"op":34,"st":3,"ct":1,"bm":0},{"ddd":0,"ind":53,"ty":0,"nm":"pre-01","refId":"comp_0","sr":1,"ks":{"o":{"a":1,"k":[{"i":{"x":[0.25],"y":[1]},"o":{"x":[0.75],"y":[0]},"t":2,"s":[100]},{"t":32,"s":[0]}],"ix":11},"r":{"a":1,"k":[{"i":{"x":[0.667],"y":[1]},"o":{"x":[0.75],"y":[0]},"t":2,"s":[0]},{"t":32,"s":[-149]}],"ix":10},"p":{"a":1,"k":[{"i":{"x":0.25,"y":1},"o":{"x":0.333,"y":0},"t":2,"s":[500,51,0],"to":[-236,327,0],"ti":[252.101,-476.396,0]},{"t":32,"s":[413.899,1416.396,0]}],"ix":2,"l":2},"a":{"a":0,"k":[50,50,0],"ix":1,"l":2},"s":{"a":1,"k":[{"i":{"x":[0.25,0.25,0.25],"y":[1,1,1]},"o":{"x":[0.333,0.333,0.333],"y":[0,0,0]},"t":2,"s":[0,0,100]},{"t":32,"s":[150,150,100]}],"ix":6,"l":2}},"ao":0,"w":100,"h":100,"ip":2,"op":33,"st":2,"ct":1,"bm":0},{"ddd":0,"ind":54,"ty":0,"nm":"pre-01","refId":"comp_0","sr":1,"ks":{"o":{"a":1,"k":[{"i":{"x":[0.25],"y":[1]},"o":{"x":[0.75],"y":[0]},"t":1,"s":[100]},{"t":31,"s":[0]}],"ix":11},"r":{"a":1,"k":[{"i":{"x":[0.667],"y":[1]},"o":{"x":[0.75],"y":[0]},"t":1,"s":[0]},{"t":31,"s":[190]}],"ix":10},"p":{"a":1,"k":[{"i":{"x":0.25,"y":1},"o":{"x":0.333,"y":0},"t":1,"s":[500,51,0],"to":[0,0,0],"ti":[-428.899,-618.396,0]},{"t":31,"s":[547.899,1416.396,0]}],"ix":2,"l":2},"a":{"a":0,"k":[50,50,0],"ix":1,"l":2},"s":{"a":1,"k":[{"i":{"x":[0.25,0.25,0.25],"y":[1,1,1]},"o":{"x":[0.333,0.333,0.333],"y":[0,0,0]},"t":1,"s":[0,0,100]},{"t":31,"s":[150,150,100]}],"ix":6,"l":2}},"ao":0,"w":100,"h":100,"ip":1,"op":32,"st":1,"ct":1,"bm":0},{"ddd":0,"ind":55,"ty":0,"nm":"pre-01","refId":"comp_0","sr":1,"ks":{"o":{"a":1,"k":[{"i":{"x":[0.25],"y":[1]},"o":{"x":[0.75],"y":[0]},"t":0,"s":[100]},{"t":30,"s":[0]}],"ix":11},"r":{"a":1,"k":[{"i":{"x":[0.25],"y":[1]},"o":{"x":[0.333],"y":[0]},"t":0,"s":[0]},{"t":30,"s":[360]}],"ix":10},"p":{"a":1,"k":[{"i":{"x":0.25,"y":1},"o":{"x":0.333,"y":0},"t":0,"s":[500,51,0],"to":[0,0,0],"ti":[321.101,-729.396,0]},{"t":30,"s":[290.899,1416.396,0]}],"ix":2,"l":2},"a":{"a":0,"k":[50,50,0],"ix":1,"l":2},"s":{"a":1,"k":[{"i":{"x":[0.25,0.25,0.25],"y":[1,1,1]},"o":{"x":[0.333,0.333,0.333],"y":[0,0,0]},"t":0,"s":[0,0,100]},{"t":30,"s":[150,150,100]}],"ix":6,"l":2}},"ao":0,"w":100,"h":100,"ip":0,"op":31,"st":0,"ct":1,"bm":0}],"markers":[{"tm":0,"cm":"","dr":0},{"tm":90,"cm":"","dr":0}]}